artemis/__init__.py
artemis/_utilities/__init__.py
artemis/_utilities/_handler.py
artemis/_utilities/domain.py
artemis/_utilities/exceptions.py
artemis/_utilities/ops.py
artemis/_utilities/pd_calculator.py
artemis/_utilities/performance_metrics.py
artemis/_utilities/split_score_metrics.py
artemis/_utilities/zenplot.py
artemis/additivity/__init__.py
artemis/additivity/_additivity_meter.py
artemis/comparison/__init__.py
artemis/comparison/_method_comparator.py
artemis/importance_methods/__init__.py
artemis/importance_methods/_method.py
artemis/importance_methods/model_agnostic/__init__.py
artemis/importance_methods/model_agnostic/_pdp.py
artemis/importance_methods/model_agnostic/_permutational_importance.py
artemis/importance_methods/model_specific/__init__.py
artemis/importance_methods/model_specific/_minimal_depth.py
artemis/importance_methods/model_specific/_split_score.py
artemis/interactions_methods/__init__.py
artemis/interactions_methods/_method.py
artemis/interactions_methods/model_agnostic/__init__.py
artemis/interactions_methods/model_agnostic/partial_dependence_based/__init__.py
artemis/interactions_methods/model_agnostic/partial_dependence_based/_friedman_h_statistic.py
artemis/interactions_methods/model_agnostic/partial_dependence_based/_greenwell.py
artemis/interactions_methods/model_agnostic/partial_dependence_based/_pdp.py
artemis/interactions_methods/model_agnostic/performance_based/__init__.py
artemis/interactions_methods/model_agnostic/performance_based/_sejong_oh.py
artemis/interactions_methods/model_specific/__init__.py
artemis/interactions_methods/model_specific/gb_trees/__init__.py
artemis/interactions_methods/model_specific/gb_trees/_split_score.py
artemis/interactions_methods/model_specific/random_forest/__init__.py
artemis/interactions_methods/model_specific/random_forest/_conditional_minimal_depth.py
artemis/visualizer/__init__.py
artemis/visualizer/_configuration.py
artemis/visualizer/_pdp_visualizer.py
artemis/visualizer/_visualizer.py
pyartemis-0.1.5.dist-info/LICENSE
pyartemis-0.1.5.dist-info/METADATA
pyartemis-0.1.5.dist-info/WHEEL
pyartemis-0.1.5.dist-info/RECORD
