Metadata-Version: 2.1
Name: pyartemis
Version: 0.1.5
Summary: A Python package with explanation methods for extraction of feature interactions from predictive models
Keywords: interactions,xai,Explainable Artificial Intelligence,explanations,machine learning,iml,Interpretable Machine Learning
Author: Artur Żółkowski
Author-email: artur.zolkowski@wp.pl
Requires-Python: >=3.8,<4.0
Classifier: Programming Language :: Python :: 3
Classifier: Programming Language :: Python :: 3.8
Classifier: Programming Language :: Python :: 3.9
Classifier: Programming Language :: Python :: 3.10
Classifier: Programming Language :: Python :: 3.11
Classifier: Programming Language :: Python :: 3.12
Requires-Dist: ipykernel (>=6.17.0,<7.0.0)
Requires-Dist: networkx (>=2.8.8,<3.0.0)
Requires-Dist: numpy (>=1.22.0,<2.0.0)
Requires-Dist: pandas (>=1.5.1,<2.0.0)
Requires-Dist: scikit-learn (>=1.1.3,<2.0.0)
Requires-Dist: seaborn (>=0.12.1,<0.13.0)
Requires-Dist: tqdm (>=4.64.1,<5.0.0)
Project-URL: Documentation, https://pyartemis.github.io/
